{
    "key_name": "ECS-key",
    "subnet_id": "subnet-060586d9be5b6ed9e",
    "albextrasubnet": "subnet-0ac1fb98cb711c23b",
    "subnets": ["subnet-060586d9be5b6ed9e", "subnet-0ac1fb98cb711c23b"],
    "vpc_id": "vpc-030210a94e6675ff6",
    "security_groups": ["sg-0e2746b37c78416a7"],
    "ecs_cluster": "PS-Prod-Cluster",
    "uniqueflagvalue": "X140",
    "volume_size": "30",
    "instance_type": "t2.micro",
    "role_name": "arn:aws:iam::806483491539:instance-profile/ecsInstanceRole",
    "tags": {
        "env": "prod",
        "uai": "1010163"
    },
    "max_instance_size": "2",
    "min_instance_size": "1",
    "desired_capacity": "1"
}